antistasi_logbook/__init__.py
antistasi_logbook/__main__.py
antistasi_logbook/app_icon.ico
antistasi_logbook/apsw.cp310-win_amd64.pyd
antistasi_logbook/apsw.cp39-win_amd64.pyd
antistasi_logbook/backend.py
antistasi_logbook/errors.py
antistasi_logbook/types.py
antistasi_logbook/data/__init__.py
antistasi_logbook/data/color_config.ini
antistasi_logbook/data/color_configspec.json
antistasi_logbook/data/content_types.py
antistasi_logbook/data/general_config.ini
antistasi_logbook/data/general_configspec.json
antistasi_logbook/data/misc.py
antistasi_logbook/data/sqf_syntax_data.py
antistasi_logbook/data/coordinates/__init__.py
antistasi_logbook/data/coordinates/chernarus_winter_pos.json
antistasi_logbook/data/map_images/__init__.py
antistasi_logbook/data/map_images/altis_thumbnail.png
antistasi_logbook/data/map_images/anizay_thumbnail.png
antistasi_logbook/data/map_images/cherno_summer_thumbnail.png
antistasi_logbook/data/map_images/cherno_winter_thumbnail.png
antistasi_logbook/data/map_images/kunduz_thumbnail.png
antistasi_logbook/data/map_images/malden_thumbnail.png
antistasi_logbook/data/map_images/sahrani_thumbnail.png
antistasi_logbook/data/map_images/stratis_thumbnail.png
antistasi_logbook/data/map_images/takistan_thumbnail.png
antistasi_logbook/data/map_images/tanoa_thumbnail.png
antistasi_logbook/data/map_images/tembelan_thumbnail.png
antistasi_logbook/data/map_images/virolahti_thumbnail.png
antistasi_logbook/gui/__init__.py
antistasi_logbook/gui/application.py
antistasi_logbook/gui/main_widget.py
antistasi_logbook/gui/main_window.py
antistasi_logbook/gui/menu_bar.py
antistasi_logbook/gui/misc.py
antistasi_logbook/gui/settings_window.py
antistasi_logbook/gui/status_bar.py
antistasi_logbook/gui/sys_tray.py
antistasi_logbook/gui/graphic/__init__.py
antistasi_logbook/gui/models/__init__.py
antistasi_logbook/gui/models/arma_function_model.py
antistasi_logbook/gui/models/base_query_data_model.py
antistasi_logbook/gui/models/game_map_model.py
antistasi_logbook-0.4.5.dist-info/entry_points.txt
antistasi_logbook-0.4.5.dist-info/LICENSE
antistasi_logbook-0.4.5.dist-info/WHEEL
antistasi_logbook-0.4.5.dist-info/METADATA
antistasi_logbook-0.4.5.dist-info/RECORD
