Metadata-Version: 2.1
Name: antistasi_logbook
Version: 0.4.5
Summary: Antistasi Logbook
Author: antistasi_tools
Requires-Python: >=3.9
Classifier: License :: OSI Approved :: MIT License
Requires-Dist: Cython>=0.29.28
Requires-Dist: PySide6>=6.2.3
Requires-Dist: anyio>=3.5.0
Requires-Dist: appdirs>=1.4.4
Requires-Dist: attrs>=21.4.0
Requires-Dist: PyGithub>=1.55
Requires-Dist: certifi>=2021.10.8
Requires-Dist: cffi>=1.15.0
Requires-Dist: charset-normalizer>=2.0.10
Requires-Dist: colorhash>=1.0.4
Requires-Dist: cryptography>=36.0.1
Requires-Dist: gidapptools>=0.2.3
Requires-Dist: httpcore==0.13.7
Requires-Dist: httpx>=0.20.0
Requires-Dist: inflect>=5.3.0
Requires-Dist: jinja2>=2.11.3
Requires-Dist: matplotlib>=3.5.1
Requires-Dist: multidict>=5.2.0
Requires-Dist: natsort>=8.0.2
Requires-Dist: numpy>=1.22.0
Requires-Dist: peewee>=3.14.8
Requires-Dist: pillow~=8.4.0
Requires-Dist: markupsafe>=2.0.1
Requires-Dist: platformdirs~=2.5.1
Requires-Dist: pp-ez==0.2.0
Requires-Dist: pprintpp==0.4.0
Requires-Dist: psutil==5.9.0
Requires-Dist: py-notifier==0.3.2
Requires-Dist: pycparser>=2.21
Requires-Dist: pygments>=2.11.2
Requires-Dist: pyparsing>=3.0.6
Requires-Dist: pyqtgraph>=0.12.3
Requires-Dist: python-dateutil>=2.8.2
Requires-Dist: python-dotenv>=0.19.2
Requires-Dist: pytz>=2021.3
Requires-Dist: qdarkstyle>=3.0.3
Requires-Dist: qt-material>=2.8.19
Requires-Dist: qtawesome>=1.1.1
Requires-Dist: rich>=12.0.0
Requires-Dist: sortedcontainers>=2.4.0
Requires-Dist: tzdata>=2021.5
Requires-Dist: tzlocal>=4.1
Requires-Dist: uritools>=4.0.0
Requires-Dist: urlextract>=1.5.0
Requires-Dist: webdav4>=0.9.3
Requires-Dist: yarl>=1.7.2
Requires-Dist: keyring>=23.5.0
Requires-Dist: frozendict==2.3.0
Project-URL: Source, https://github.com/Giddius/Antistasi_Logbook
